MANIFEST.in
README.md
setup.py
setup_travis.py
./gui/AlignmentGUI.py
./gui/TAPIR.py
analysis/alignment/compute_full_matrix.py
analysis/alignment/extract_matrix.py
analysis/alignment/feature_alignment.py
analysis/alignment/preprocess_peakview.py
analysis/alignment/requantAlignedValues.py
analysis/data_conversion/MSE2mzML.py
analysis/data_conversion/MSE_split.py
analysis/data_conversion/convertFromPeakview.py
analysis/data_conversion/featurealigner2msstats.py
analysis/data_conversion/filterPeakview.py
analysis/data_conversion/fix_sonar.py
analysis/data_conversion/fix_swath_windows.py
analysis/data_conversion/pepxml2csv.py
analysis/data_conversion/pepxml2csv_simple.py
analysis/data_conversion/pseudoreverseDB.py
analysis/data_conversion/split_mzXML_intoSwath.py
analysis/fdr_estimation/ProtFDRTraML2Fasta.py
analysis/fdr_estimation/ProtFDRmProphet2Mayu.py
analysis/mProphet/count_pep_prot.py
analysis/mProphet/fdr_cutoff.py
analysis/misc/proteinDBmasses.py
analysis/misc/proteinDigest.py
analysis/misc/trafoXML_visualize.py
analysis/scripts/add_protein_annotation.py
analysis/scripts/convertNISTLibraryToTSV.py
analysis/scripts/copy_accesion.py
analysis/scripts/filterChrom.py
analysis/scripts/filterSqMass.py
analysis/scripts/mergeSqMass.py
analysis/scripts/plot_alignment_tree.py
analysis/scripts/proteins_not_in_library.py
analysis/scripts/DIA/NISTParser.py
analysis/scripts/DIA/convertMassLynxTomzML.py
analysis/scripts/DIA/makeSwathFile.py
analysis/scripts/DIA/splitMSE.py
analysis/spectral_libs/spectrast2spectrast_irt.py
analysis/spectral_libs/spectrast2tsv.py
analysis/spectral_libs/spectrast_cluster.py
analysis/spectral_libs/spectrast_updateiRTs.py
analysis/spectral_libs/tsv2spectrast.py
gui/AlignmentGUI.py
gui/TAPIR.py
gui/openswathgui/__init__.py
gui/openswathgui/models/ChromatogramTransition.py
gui/openswathgui/models/MSData.py
gui/openswathgui/models/PeptideTree.py
gui/openswathgui/models/SwathRunCollection.py
gui/openswathgui/models/TreeModels.py
msproteomicstools.egg-info/PKG-INFO
msproteomicstools.egg-info/SOURCES.txt
msproteomicstools.egg-info/dependency_links.txt
msproteomicstools.egg-info/requires.txt
msproteomicstools.egg-info/top_level.txt
